Metadata-Version: 2.4
Name: IMTreatment
Version: 1.4.2
Summary: Tools to analyze scalar and vector fields
Author-email: Gaby Launay <gaby.launay@protonmail.com>
License: GPLv3
Project-URL: Homepage, https://framagit.org/gabylaunay/IMTreatment
Keywords: scalarfield,vectorfield,fluid dynamics,PIV,vortex
Classifier: Development Status :: 5 - Production/Stable
Classifier: Intended Audience :: Science/Research
Classifier: Topic :: Scientific/Engineering
Classifier: Programming Language :: Python :: 3 :: Only
Classifier: Natural Language :: English
Classifier: License :: OSI Approved :: GNU General Public License v3 (GPLv3)
Classifier: Operating System :: OS Independent
Requires-Python: >=3.10
License-File: LICENSE
Requires-Dist: numpy>=2.2.3
Requires-Dist: matplotlib>=3.10.0
Requires-Dist: scipy>=1.15.2
Requires-Dist: unum>=4.2.1
Requires-Dist: imageio>=2.37.0
Requires-Dist: multiprocess>=0.70.17
Requires-Dist: psutil>=7.0.0
Requires-Dist: colorama>=0.4.6
Requires-Dist: pywavelets>=1.8.0
Dynamic: license-file
